[
    {
        "art_uuid": "ef5b2d39-4aa4-4242-a640-7a466e635574",
        "request_timestamp": "2026-04-28 03:48:30",
        "art_name": "Idk js a sweaty cat (test)",
        "creation_date": "17.05.2025",
        "link": "https://soperfect.nekoweb.org/test131.png"
    },
    {
        "art_uuid": "a7959521-c900-4991-9f69-2b2d5759c232",
        "request_timestamp": "2026-04-28 04:57:20",
        "art_name": "test 1:1",
        "creation_date": "01.01.1900",
        "link": "https://lh3.googleusercontent.com/_qFg6CNukCb16V5nhqs7SXL8bo6_YBdJksoygArVJ3oRoR-6_EKBNpK-QojrQ-ZxUpB6AEW6mvstKzD5rw=w544-h544-l90-rj"
    }
]